{
  "symbol": "GC=F",
  "tz": "America/New_York",
  "price": 4038.5,
  "priorClose": 3990.3,
  "changePts": 48.2,
  "changePct": 1.2,
  "today": {
    "open": 4029.9,
    "high": 4038.5,
    "low": 4026.3,
    "usedPts": 12.2,
    "rangeUsedPct": 14
  },
  "adr": 90.2,
  "adrProjection": {
    "upFromLow": 4116.5,
    "downFromHigh": 3948.3
  },
  "sessions": {
    "asia": {
      "high": 4038.5,
      "low": 4026.3,
      "open": 4029.9,
      "close": 4038.5
    },
    "london": null
  },
  "priorDay": {
    "high": 4104.7,
    "low": 3963.3,
    "close": 3990.3
  },
  "pivots": {
    "p": 4019.4,
    "r1": 4075.6,
    "s1": 3934.2,
    "r2": 4160.8,
    "s2": 3878,
    "r3": 4217,
    "s3": 3792.8
  },
  "roundLevels": [
    3975,
    4000,
    4025,
    4050,
    4075,
    4100
  ],
  "read": {
    "probabilityUp": 65,
    "bias": "Long",
    "confidence": "Medium",
    "keyLevel": 4025,
    "scenarioUp": "If 4025 holds, look for a push towards R1 (4075.6) and potentially 4100.",
    "scenarioDown": "Break below 4025 could see a retest of P (4019.4) then S1 (3934.2).",
    "note": "Price is currently at the day's high, with only 14% of ADR used, suggesting room for continuation. Above 4025 is bullish."
  },
  "dataLive": true,
  "generatedAt": "2026-06-26T00:56:44.582Z",
  "nextRunAt": "2026-06-26T04:56:44.582Z"
}